Metadata-Version: 1.1
Name: QMS
Version: 0.5.1dev1
Summary: Query Made Simple
Home-page: https://github.com/arno06/QMS
Author: Arnaud NICOLAS
Author-email: arno06@gmail.com
License: MIT
Keywords: mysql querybuiler
Platform: UNKNOWN
Classifier: Development Status :: 3 - Alpha
Classifier: Intended Audience :: Developers
Classifier: License :: OSI Approved :: MIT License
Classifier: Programming Language :: Python :: 3.4
